piflib/__init__.py
piflib/data_util.py
piflib/entropy.py
piflib/pif_calculator.py
piflib-0.1.1.dist-info/LICENSE
piflib-0.1.1.dist-info/METADATA
piflib-0.1.1.dist-info/WHEEL
piflib-0.1.1.dist-info/top_level.txt
piflib-0.1.1.dist-info/RECORD
