Metadata-Version: 2.1
Name: piflib
Version: 0.1.1
Summary: A library for computing the personal information factor (PIF)
Home-page: https://github.com/PIFtools/piflib
Author: CSIRO's DATA61
Author-email: confidential.computing@data61.csiro.au
License: Apache
Project-URL: Documentation, http://piflib.readthedocs.io/
Project-URL: Source, https://github.com/PIFtools/piflib
Project-URL: Tracker, https://github.com/PIFtools/piflib/issues
Project-URL: Discussion, https://github.com/PIFtools/piflib/discussions
Platform: UNKNOWN
Classifier: Programming Language :: Python :: 3
Classifier: Intended Audience :: Developers
Classifier: License :: OSI Approved :: Apache Software License
Classifier: Operating System :: OS Independent
Requires-Dist: numpy (>=1.19.0)
Requires-Dist: pandas (>=1.1.0)
